README.rst
setup.py
hmsclient/__init__.py
hmsclient/hmsclient.py
hmsclient/genthrift/__init__.py
hmsclient/genthrift/fb303/FacebookService.py
hmsclient/genthrift/fb303/__init__.py
hmsclient/genthrift/fb303/constants.py
hmsclient/genthrift/fb303/ttypes.py
hmsclient/genthrift/hive_metastore/ThriftHiveMetastore.py
hmsclient/genthrift/hive_metastore/__init__.py
hmsclient/genthrift/hive_metastore/constants.py
hmsclient/genthrift/hive_metastore/ttypes.py
hmsclient_hive_3.egg-info/PKG-INFO
hmsclient_hive_3.egg-info/SOURCES.txt
hmsclient_hive_3.egg-info/dependency_links.txt
hmsclient_hive_3.egg-info/requires.txt
hmsclient_hive_3.egg-info/top_level.txt