Metadata-Version: 2.1
Name: hmsclient-hive-3
Version: 0.1.1
Summary: A package interact with the Hive metastore (API version 3.0) via the Thrift protocol
Home-page: https://github.com/itamarla/hmsclient-hive-3
Author: https://github.com/itamarla/hmsclient-hive-3
Author-email: itamar@itamar.org
License: Apache 2.0
Keywords: hive data database thrift metastore
Platform: UNKNOWN
Classifier: Development Status :: 4 - Beta
Classifier: Intended Audience :: Information Technology
Classifier: Topic :: Database
Classifier: License :: OSI Approved :: Apache Software License
Classifier: Programming Language :: Python :: 3
Classifier: Programming Language :: Python :: 3.5
Classifier: Programming Language :: Python :: 3.6
Classifier: Programming Language :: Python :: 3.7
Provides-Extra: dev
Provides-Extra: test
